Workbook

Sheet Company Ratings
A1: Company | B1: City | C1: Platform / source type | D1: Rating | E1: Review count | F1: Primary source URL | G1: Verification status | H1: Notes
A2: LearnMore Technologies | B2: Coimbatore | C2: Official website / testimonials | D2: 4.9/5 (company-published claim) | E2: 3,200+ (company-published claim) | F2: https://learnmoretechnologies.in/testimonials | G2: Company-published claim; independent profile not verified | H2: Website describes its rating as Google and platform rating; confirm the correct local business profile before comparing | I2: =TRIM(A2) -> LearnMore Technologies | J2: =IFERROR(INDEX('Company Ratings'!$D$2:$D$1000,MATCH(TRIM(A2),'Company Ratings'!$A$2:$A$1000,0)),"No matching rating") -> 4.9/5 (company-published claim) | K2: {=IFERROR(_xlfn.TEXTJOIN(CHAR(10),TRUE,_xlfn._xlws.FILTER('Company Ratings'!$C$2:$C$1000&" — "&'Company Ratings'!$D$2:$D$1000,'Company Ratings'!$A$2:$A$1000=TRIM(A2))),"No matching rating")} -> Official website / testimonials — 4.9/5 (company-published claim) | L2: {=IFERROR(_xlfn.TEXTJOIN(CHAR(10),TRUE,_xlfn._xlws.FILTER('Company Ratings'!$C$2:$C$1000&" — "&'Company Ratings'!$D$2:$D$1000,'Company Ratings'!$A$2:$A$1000=TRIM(A2))),"No matching rating")} -> Official website / testimonials — 4.9/5 (company-published claim)
A3: Yale Infotech | B3: Coimbatore | C3: Google rating reported by Localo | D3: 4.9/5 | E3: 937 | F3: https://yale-infotech-coimbatore.localo.site/ | G3: Third-party reported; direct Google profile verification pending | H3: Reported listing is for Yale Infotech Coimbatore; confirm business identity | I3: =TRIM(A3) -> Yale Infotech | J3: =IFERROR(INDEX('Company Ratings'!$D$2:$D$1000,MATCH(TRIM(A3),'Company Ratings'!$A$2:$A$1000,0)),"No matching rating") -> 4.9/5 | K3: {=IFERROR(_xlfn.TEXTJOIN(CHAR(10),TRUE,_xlfn._xlws.FILTER('Company Ratings'!$C$2:$C$1000&" — "&'Company Ratings'!$D$2:$D$1000,'Company Ratings'!$A$2:$A$1000=TRIM(A3))),"No matching rating")} -> Google rating reported by Localo — 4.9/5 | L3: {=IFERROR(_xlfn.TEXTJOIN(CHAR(10),TRUE,_xlfn._xlws.FILTER('Company Ratings'!$C$2:$C$1000&" — "&'Company Ratings'!$D$2:$D$1000,'Company Ratings'!$A$2:$A$1000=TRIM(A3))),"No matching rating")} -> Google rating reported by Localo — 4.9/5
A4: Digital Scholar | B4: Chennai | C4: Google reviews reported by Collegedunia | D4: 4.7/5 | E4: 3246 | F4: https://collegedunia.com/institute/3894-digital-scholar-digital-marketing-training-institute-chennai/google-reviews | G4: Third-party reported; current profile verification pending | H4: Keep separate from Trustpilot rating | I4: =TRIM(A4) -> Digital Scholar | J4: =IFERROR(INDEX('Company Ratings'!$D$2:$D$1000,MATCH(TRIM(A4),'Company Ratings'!$A$2:$A$1000,0)),"No matching rating") -> 4.7/5 | K4: {=IFERROR(_xlfn.TEXTJOIN(CHAR(10),TRUE,_xlfn._xlws.FILTER('Company Ratings'!$C$2:$C$1000&" — "&'Company Ratings'!$D$2:$D$1000,'Company Ratings'!$A$2:$A$1000=TRIM(A4))),"No matching rating")} -> Google reviews reported by Collegedunia — 4.7/5 Trustpilot — 3.6/5 | L4: {=IFERROR(_xlfn.TEXTJOIN(CHAR(10),TRUE,_xlfn._xlws.FILTER('Company Ratings'!$C$2:$C$1000&" — "&'Company Ratings'!$D$2:$D$1000,'Company Ratings'!$A$2:$A$1000=TRIM(A4))),"No matching rating")} -> Google reviews reported by Collegedunia — 4.7/5 Trustpilot — 3.6/5
A5: Digital Scholar | B5: Chennai | C5: Trustpilot | D5: 3.6/5 | E5: 490 | F5: https://www.trustpilot.com/review/digitalscholar.in | G5: Source page reports these figures; recheck before submission | H5: Different platform from Google; do not average the ratings | I5: =TRIM(A5) -> Digital Scholar | J5: =IFERROR(INDEX('Company Ratings'!$D$2:$D$1000,MATCH(TRIM(A5),'Company Ratings'!$A$2:$A$1000,0)),"No matching rating") -> 4.7/5 | K5: {=IFERROR(_xlfn.TEXTJOIN(CHAR(10),TRUE,_xlfn._xlws.FILTER('Company Ratings'!$C$2:$C$1000&" — "&'Company Ratings'!$D$2:$D$1000,'Company Ratings'!$A$2:$A$1000=TRIM(A5))),"No matching rating")} -> Google reviews reported by Collegedunia — 4.7/5 Trustpilot — 3.6/5 | L5: {=IFERROR(_xlfn.TEXTJOIN(CHAR(10),TRUE,_xlfn._xlws.FILTER('Company Ratings'!$C$2:$C$1000&" — "&'Company Ratings'!$D$2:$D$1000,'Company Ratings'!$A$2:$A$1000=TRIM(A5))),"No matching rating")} -> Google reviews reported by Collegedunia — 4.7/5 Trustpilot — 3.6/5
A6: Aurobotix Systems | B6: Chennai | C6: Justdial | D6: 4.9/5 | E6: 45 | F6: https://m.justdial.com/jdmart/Chennai/All-Workstation-Programming-Software/pid-803069080/044PXX44-XX44-260422133229-U6Y9 | G6: Listing found; exact business/course relevance needs confirmation | H6: Justdial listing identifies Aurobotix Systems; verify that the profile is appropriate for training-course comparisons | I6: =TRIM(A6) -> Aurobotix Systems | J6: =IFERROR(INDEX('Company Ratings'!$D$2:$D$1000,MATCH(TRIM(A6),'Company Ratings'!$A$2:$A$1000,0)),"No matching rating") -> 4.9/5 | K6: {=IFERROR(_xlfn.TEXTJOIN(CHAR(10),TRUE,_xlfn._xlws.FILTER('Company Ratings'!$C$2:$C$1000&" — "&'Company Ratings'!$D$2:$D$1000,'Company Ratings'!$A$2:$A$1000=TRIM(A6))),"No matching rating")} -> Justdial — 4.9/5 | L6: {=IFERROR(_xlfn.TEXTJOIN(CHAR(10),TRUE,_xlfn._xlws.FILTER('Company Ratings'!$C$2:$C$1000&" — "&'Company Ratings'!$D$2:$D$1000,'Company Ratings'!$A$2:$A$1000=TRIM(A6))),"No matching rating")} -> Justdial — 4.9/5
A7: Fulcrum Creative School | B7: Coimbatore | C7: Official website | D7: 4.9 stars (site claim) | E7: Not captured | F7: https://fulcrumtechcbe.com/ | G7: Company-published claim; review count pending | H7: Do not interpret the site claim as independently verified | I7: =TRIM(A7) -> Fulcrum Creative School | J7: =IFERROR(INDEX('Company Ratings'!$D$2:$D$1000,MATCH(TRIM(A7),'Company Ratings'!$A$2:$A$1000,0)),"No matching rating") -> 4.9 stars (site claim) | K7: {=IFERROR(_xlfn.TEXTJOIN(CHAR(10),TRUE,_xlfn._xlws.FILTER('Company Ratings'!$C$2:$C$1000&" — "&'Company Ratings'!$D$2:$D$1000,'Company Ratings'!$A$2:$A$1000=TRIM(A7))),"No matching rating")} -> Official website — 4.9 stars (site claim) Justdial — 4.7/5 | L7: {=IFERROR(_xlfn.TEXTJOIN(CHAR(10),TRUE,_xlfn._xlws.FILTER('Company Ratings'!$C$2:$C$1000&" — "&'Company Ratings'!$D$2:$D$1000,'Company Ratings'!$A$2:$A$1000=TRIM(A7))),"No matching rating")} -> Official website — 4.9 stars (site claim) Justdial — 4.7/5
A8: Fulcrum Creative School | B8: Coimbatore | C8: Justdial | D8: 4.7/5 | E8: 24 | F8: https://www.justdial.com/Coimbatore/Fulcrum-Creative-School-Animation-Courses-In-Gandhipuram/0422PX422-X422-250813153334-G5P9 | G8: Third-party reported; current profile verification pending | H8: Confirm correct listing and current count | I8: =TRIM(A8) -> Fulcrum Creative School | J8: =IFERROR(INDEX('Company Ratings'!$D$2:$D$1000,MATCH(TRIM(A8),'Company Ratings'!$A$2:$A$1000,0)),"No matching rating") -> 4.9 stars (site claim) | K8: {=IFERROR(_xlfn.TEXTJOIN(CHAR(10),TRUE,_xlfn._xlws.FILTER('Company Ratings'!$C$2:$C$1000&" — "&'Company Ratings'!$D$2:$D$1000,'Company Ratings'!$A$2:$A$1000=TRIM(A8))),"No matching rating")} -> Official website — 4.9 stars (site claim) Justdial — 4.7/5 | L8: {=IFERROR(_xlfn.TEXTJOIN(CHAR(10),TRUE,_xlfn._xlws.FILTER('Company Ratings'!$C$2:$C$1000&" — "&'Company Ratings'!$D$2:$D$1000,'Company Ratings'!$A$2:$A$1000=TRIM(A8))),"No matching rating")} -> Official website — 4.9 stars (site claim) Justdial — 4.7/5
A9: ICAT Design and Media College | B9: Chennai | C9: Google rating reported by Collegedunia | D9: 4.1/5 | E9: 289 | F9: https://collegedunia.com/institute/4451-icat-design-and-media-college-chennai | G9: Third-party reported; current profile verification pending | H9: Use as a platform-specific rating lead, not an official college rating | I9: =TRIM(A9) -> ICAT Design and Media College | J9: =IFERROR(INDEX('Company Ratings'!$D$2:$D$1000,MATCH(TRIM(A9),'Company Ratings'!$A$2:$A$1000,0)),"No matching rating") -> 4.1/5 | K9: {=IFERROR(_xlfn.TEXTJOIN(CHAR(10),TRUE,_xlfn._xlws.FILTER('Company Ratings'!$C$2:$C$1000&" — "&'Company Ratings'!$D$2:$D$1000,'Company Ratings'!$A$2:$A$1000=TRIM(A9))),"No matching rating")} -> Google rating reported by Collegedunia — 4.1/5 Justdial — 3.8/5 | L9: {=IFERROR(_xlfn.TEXTJOIN(CHAR(10),TRUE,_xlfn._xlws.FILTER('Company Ratings'!$C$2:$C$1000&" — "&'Company Ratings'!$D$2:$D$1000,'Company Ratings'!$A$2:$A$1000=TRIM(A9))),"No matching rating")} -> Google rating reported by Collegedunia — 4.1/5 Justdial — 3.8/5
A10: ICAT Design and Media College | B10: Chennai | C10: Justdial | D10: 3.8/5 | E10: 539 | F10: https://www.justdial.com/Chennai/ICAT-Design-And-Media-College-Opposite-St-Beds-School-Mylapore/044PF009779_BZDET/reviews | G10: Third-party reported; current profile verification pending | H10: Keep separate from Google rating | I10: =TRIM(A10) -> ICAT Design and Media College | J10: =IFERROR(INDEX('Company Ratings'!$D$2:$D$1000,MATCH(TRIM(A10),'Company Ratings'!$A$2:$A$1000,0)),"No matching rating") -> 4.1/5 | K10: {=IFERROR(_xlfn.TEXTJOIN(CHAR(10),TRUE,_xlfn._xlws.FILTER('Company Ratings'!$C$2:$C$1000&" — "&'Company Ratings'!$D$2:$D$1000,'Company Ratings'!$A$2:$A$1000=TRIM(A10))),"No matching rating")} -> Google rating reported by Collegedunia — 4.1/5 Justdial — 3.8/5 | L10: {=IFERROR(_xlfn.TEXTJOIN(CHAR(10),TRUE,_xlfn._xlws.FILTER('Company Ratings'!$C$2:$C$1000&" — "&'Company Ratings'!$D$2:$D$1000,'Company Ratings'!$A$2:$A$1000=TRIM(A10))),"No matching rating")} -> Google rating reported by Collegedunia — 4.1/5 Justdial — 3.8/5
A11: L. V. Prasad College of Media Studies | B11: Chennai | C11: Justdial | D11: 4.3/5 | E11: 233 | F11: https://www.justdial.com/Chennai/L-V-Prasad-College-Of-Media-Studies-Inside-Prasad-Studios-Saligramam/044PXX44-XX44-090624174838-K2C9_BZDET/reviews | G11: Third-party reported; current profile verification pending | H11: Confirm that this is the relevant college profile | I11: =TRIM(A11) -> L. V. Prasad College of Media Studies | J11: =IFERROR(INDEX('Company Ratings'!$D$2:$D$1000,MATCH(TRIM(A11),'Company Ratings'!$A$2:$A$1000,0)),"No matching rating") -> 4.3/5 | K11: {=IFERROR(_xlfn.TEXTJOIN(CHAR(10),TRUE,_xlfn._xlws.FILTER('Company Ratings'!$C$2:$C$1000&" — "&'Company Ratings'!$D$2:$D$1000,'Company Ratings'!$A$2:$A$1000=TRIM(A11))),"No matching rating")} -> Justdial — 4.3/5 | L11: {=IFERROR(_xlfn.TEXTJOIN(CHAR(10),TRUE,_xlfn._xlws.FILTER('Company Ratings'!$C$2:$C$1000&" — "&'Company Ratings'!$D$2:$D$1000,'Company Ratings'!$A$2:$A$1000=TRIM(A11))),"No matching rating")} -> Justdial — 4.3/5
A12: AIRA Global Tech | B12: Coimbatore | C12: Official website | D12: Not verified | E12: Not verified | F12: https://www.airaglobaltech.com/ | G12: Numerical rating not verified in the earlier homepage check | H12: Do not enter zero; check the correct independent review profiles | I12: =TRIM(A12) -> AIRA Global Tech | J12: =IFERROR(INDEX('Company Ratings'!$D$2:$D$1000,MATCH(TRIM(A12),'Company Ratings'!$A$2:$A$1000,0)),"No matching rating") -> Not verified | K12: {=IFERROR(_xlfn.TEXTJOIN(CHAR(10),TRUE,_xlfn._xlws.FILTER('Company Ratings'!$C$2:$C$1000&" — "&'Company Ratings'!$D$2:$D$1000,'Company Ratings'!$A$2:$A$1000=TRIM(A12))),"No matching rating")} -> Official website — Not verified | L12: {=IFERROR(_xlfn.TEXTJOIN(CHAR(10),TRUE,_xlfn._xlws.FILTER('Company Ratings'!$C$2:$C$1000&" — "&'Company Ratings'!$D$2:$D$1000,'Company Ratings'!$A$2:$A$1000=TRIM(A12))),"No matching rating")} -> Official website — Not verified

Sheet Course Register
A1: City | B1: Course | C1: Competitor | D1: Published fee / duration | E1: Official URL | F1: Record review status | G1: Review Notes | H1: Company Rating
A2: Coimbatore | B2: Digital Marketing | C2: CIIM | D2: Fee not confirmed; exact program and duration need confirmation | E2: https://www.ciim.in/digital-marketing-course-in-coimbatore/ | F2: Official course details need confirmation | G2: Confirm the exact Digital Marketing program offered in Coimbatore, its current fee, duration, and delivery mode. CIIM lists multiple Digital Marketing programs with different durations and prices; do not assume the general catalogue price applies to this branch. Official course catalogue. | H2: {=IFERROR(_xlfn.TEXTJOIN(CHAR(10),TRUE,_xlfn._xlws.FILTER('Company Ratings'!$C$2:$C$1000&" — "&'Company Ratings'!$D$2:$D$1000,'Company Ratings'!$A$2:$A$1000=TRIM(C2))),"No matching rating — verify")} -> No matching rating — verify
A3: Chennai | B3: Digital Marketing | C3: CIIM | D3: Fee not disclosed on city page; 4 months for advertised Advanced Digital Marketing & AI Certification; classroom/online options | E3: https://www.ciim.in/digital-marketing-course-in-chennai/ | F3: Duration found on official page; fee confirmation pending | G3: The official Chennai page advertises a four-month Advanced Digital Marketing & AI Certification with classroom and online options. Fee is not clearly disclosed on the city page. Confirm the current fee and batch availability with admissions. | H3: {=IFERROR(_xlfn.TEXTJOIN(CHAR(10),TRUE,_xlfn._xlws.FILTER('Company Ratings'!$C$2:$C$1000&" — "&'Company Ratings'!$D$2:$D$1000,'Company Ratings'!$A$2:$A$1000=TRIM(C3))),"No matching rating — verify")} -> No matching rating — verify
A4: Chennai | B4: Digital Marketing | C4: Digital Scholar | D4: ₹69,999 including GST; 4 months; live online; additional project/tool costs may apply | E4: https://digitalscholar.in/ | F4: Official online course details found; confirm comparison format | G4: The official Chennai course page lists ₹69,999 including GST for a four-month program. Advertising budgets, hosting, paid tools, and API credits may incur additional costs. Confirm current fees and any extra charges before finalizing the comparison. | H4: {=IFERROR(_xlfn.TEXTJOIN(CHAR(10),TRUE,_xlfn._xlws.FILTER('Company Ratings'!$C$2:$C$1000&" — "&'Company Ratings'!$D$2:$D$1000,'Company Ratings'!$A$2:$A$1000=TRIM(C4))),"No matching rating — verify")} -> Google reviews reported by Collegedunia — 4.7/5 Trustpilot — 3.6/5
A5: Coimbatore | B5: Data Analytics | C5: LearnMore Technologies | D5: Fee not disclosed; 8 weeks / 60 hours | E5: https://learnmoretechnologies.in/locations/coimbatore/data-analytics-course | F5: Duration published; confirm fee and delivery mode | G5: Confirm current course availability, published fee and actual delivery mode for the Coimbatore branch. | H5: {=IFERROR(_xlfn.TEXTJOIN(CHAR(10),TRUE,_xlfn._xlws.FILTER('Company Ratings'!$C$2:$C$1000&" — "&'Company Ratings'!$D$2:$D$1000,'Company Ratings'!$A$2:$A$1000=TRIM(C5))),"No matching rating — verify")} -> Official website / testimonials — 4.9/5 (company-published claim)
A6: Coimbatore and Chennai | B6: Data Analytics | C6: Study Giant Academy | D6: Fee not disclosed; typically 2–3 months; online/offline options | E6: https://studygiantacademy.com/our-branches-and-courses | F6: Duration and modes published; confirm fee by city | G6: Confirm fee, duration and delivery mode separately for Coimbatore and Chennai; the published duration may vary by batch. | H6: {=IFERROR(_xlfn.TEXTJOIN(CHAR(10),TRUE,_xlfn._xlws.FILTER('Company Ratings'!$C$2:$C$1000&" — "&'Company Ratings'!$D$2:$D$1000,'Company Ratings'!$A$2:$A$1000=TRIM(C6))),"No matching rating — verify")} -> No matching rating — verify
A7: Coimbatore | B7: Data Analytics | C7: upGrad Learning Centre | D7: ₹99,999; 4 months; offline | E7: https://upgradcoimbatore.in/ | F7: Fee and duration published; confirm current offer | G7: Confirm that the ₹99,999 fee and four-month duration remain current, and verify the next Coimbatore batch and delivery format. | H7: {=IFERROR(_xlfn.TEXTJOIN(CHAR(10),TRUE,_xlfn._xlws.FILTER('Company Ratings'!$C$2:$C$1000&" — "&'Company Ratings'!$D$2:$D$1000,'Company Ratings'!$A$2:$A$1000=TRIM(C7))),"No matching rating — verify")} -> No matching rating — verify
A8: Coimbatore | B8: UI/UX Design | C8: Yale Infotech | D8: ₹24,999; 3–4 months (120+ hours); offline/online/weekend options | E8: https://www.yaleinfotech.com/course/best-ui-ux-designer-course-in-coimbatore/ | F8: Official fee, duration and delivery options published; confirm current batch and fee | G8: Confirm the current fee, instalment terms and available Coimbatore batch. Verify delivery mode and obtain the current syllabus before finalizing. | H8: {=IFERROR(_xlfn.TEXTJOIN(CHAR(10),TRUE,_xlfn._xlws.FILTER('Company Ratings'!$C$2:$C$1000&" — "&'Company Ratings'!$D$2:$D$1000,'Company Ratings'!$A$2:$A$1000=TRIM(C8))),"No matching rating — verify")} -> Google rating reported by Localo — 4.9/5
A9: Coimbatore and Chennai | B9: UI/UX Design | C9: Study Giant Academy | D9: Fee not disclosed; typically 3 months; classroom/online options | E9: https://studygiantacademy.com/our-branches-and-courses | F9: Duration and delivery options published; fee confirmation pending by city | G9: Confirm the current fee and duration for Coimbatore and Chennai separately. Verify the selected batch type, delivery mode and whether fast-track batches have a different fee or duration. | H9: {=IFERROR(_xlfn.TEXTJOIN(CHAR(10),TRUE,_xlfn._xlws.FILTER('Company Ratings'!$C$2:$C$1000&" — "&'Company Ratings'!$D$2:$D$1000,'Company Ratings'!$A$2:$A$1000=TRIM(C9))),"No matching rating — verify")} -> No matching rating — verify
A10: Chennai | B10: UI/UX Design | C10: TSDC / Traijo | D10: ₹20,000; 10 weeks; offline/hybrid | E10: https://traijoedu.in/courses/uiux-design/ | F10: Official fee, duration and delivery modes published; confirm current offer | G10: Confirm that ₹20,000 is the current total fee and ask whether taxes or other charges apply. Verify the next batch, offline/hybrid schedule and certificate conditions. | H10: {=IFERROR(_xlfn.TEXTJOIN(CHAR(10),TRUE,_xlfn._xlws.FILTER('Company Ratings'!$C$2:$C$1000&" — "&'Company Ratings'!$D$2:$D$1000,'Company Ratings'!$A$2:$A$1000=TRIM(C10))),"No matching rating — verify")} -> No matching rating — verify
A11: Chennai | B11: UI/UX Design | C11: ICAT Design and Media College | D11: Fee to confirm; 1-year full-time program; graduate eligibility to be confirmed | E11: https://www.icat.ac.in/chennai/pg-ui-ux-design-course-college.aspx | F11: Official program and duration published; current fee and eligibility confirmation pending | G11: Confirm current tuition and additional charges, graduate eligibility, intake dates and full-time attendance requirements. Verify the exact qualification awarded before comparing it with short-term certificate courses. | H11: {=IFERROR(_xlfn.TEXTJOIN(CHAR(10),TRUE,_xlfn._xlws.FILTER('Company Ratings'!$C$2:$C$1000&" — "&'Company Ratings'!$D$2:$D$1000,'Company Ratings'!$A$2:$A$1000=TRIM(C11))),"No matching rating — verify")} -> Google rating reported by Collegedunia — 4.1/5 Justdial — 3.8/5
A12: Coimbatore | B12: AI / Agentic AI | C12: Yale Infotech | D12: ₹30,000 is shown in the course facts section, while another fee section on the same page shows ₹24,999. Duration: 3–4 months / 120+ hours. Online, offline and weekend options are advertised. | E12: https://www.yaleinfotech.com/course/best-artificial-intelligence-course-in-coimbatore/ | F12: Official duration and delivery options published; conflicting fees require confirmation. | G12: The official page displays two different fees: ₹30,000 and ₹24,999. Obtain written confirmation of the current total fee, instalment terms, duration and current batch before recording a single price. | H12: {=IFERROR(_xlfn.TEXTJOIN(CHAR(10),TRUE,_xlfn._xlws.FILTER('Company Ratings'!$C$2:$C$1000&" — "&'Company Ratings'!$D$2:$D$1000,'Company Ratings'!$A$2:$A$1000=TRIM(C12))),"No matching rating — verify")} -> Google rating reported by Localo — 4.9/5
A13: Coimbatore | B13: AI / Agentic AI | C13: AIRA Global Tech | D13: ₹30,000 standard tuition; 3 months. Classroom and live online options are advertised. | E13: https://www.airaglobaltech.com/training-institute-in-coimbatore | F13: Fee, duration and delivery options published; confirm the specific AI program and current batch. | G13: The provider lists several AI programs, including Generative AI & Prompt Engineering, AI & Data Science, Machine Learning and AI Full Stack Development. Confirm which program the quoted ₹30,000 fee applies to and whether it specifically covers Agentic AI. | H13: {=IFERROR(_xlfn.TEXTJOIN(CHAR(10),TRUE,_xlfn._xlws.FILTER('Company Ratings'!$C$2:$C$1000&" — "&'Company Ratings'!$D$2:$D$1000,'Company Ratings'!$A$2:$A$1000=TRIM(C13))),"No matching rating — verify")} -> Official website — Not verified
... A26: Coimbatore | B26: Digital Marketing | C26: VersionX | D26: Total fee to confirm; 4-month in-person program plus separate 2-month paid internship | E26: https://theversionx.com/programs/ | F26: Official program details found; confirm total fee and internship terms | G26: The official website advertises a 4-month, full-time, in-person Digital Marketing Certification in Coimbatore, followed by a separate 2-month paid internship (Phase 2) at a partner agency. The admissions page displays a starting price of ₹3,910 per month, but the total course fee and one-time payment amount are not clearly established in the page text. Confirm the full payable fee, registration charges, instalment terms, and whether any additional costs apply. Verify the internship eligibility, selection conditions, stipend/payment terms, and whether the internship is guaranteed. Request the current fee structure and internship terms in writing before finalizing the comparison. | H26: {=IFERROR(_xlfn.TEXTJOIN(CHAR(10),TRUE,_xlfn._xlws.FILTER('Company Ratings'!$C$2:$C$1000&" — "&'Company Ratings'!$D$2:$D$1000,'Company Ratings'!$A$2:$A$1000=TRIM(C26))),"No matching rating — verify")} -> No matching rating — verify

Sheet Verification Tasks
A1: Verification item | B1: Current status | C1: Required action
A2: Confirm Full Stack course availability at both campuses | B2: Pending verification | C2: Check official course pages or obtain written confirmation
A3: Obtain current fee sheets | B3: Pending verification | C3: Request current fee details from each provider
A4: Confirm duration and delivery mode by course and city | B4: Pending verification | C4: Record classroom, online or hybrid mode separately
A5: Obtain official syllabus documents | B5: Pending verification | C5: Save the syllabus URL or document for each relevant course
A6: Confirm pay, eligibility, hours and deliverables | B6: Pending verification | C6: Use only where relevant to the competitor-analysis scope
A7: Request cohort-level employment data | B7: Pending verification | C7: Record the cohort, period, denominator and source if supplied
A8: Check official pages or obtain written quotations | B8: Pending verification | C8: Resolve conflicting prices and unclear claims
A9: Verify review-platform profiles | B9: Pending verification | C9: Match company, branch and city before recording ratings
A10: Record verification date | B10: Pending verification | C10: Add the date each source was actually checked
A11: Confirm CIIM Digital Marketing course duration | B11: Pending verification | C11: Resolve the 3–4 month wording conflict using the official course page
A12: Confirm competitor course fees | B12: Pending verification | C12: Record published fees or mark fee as not disclosed
... A15: Verify official source URLs | B15: Pending verification | C15: Check that each link opens and refers to the listed competitor/course
